{"AUSTRIA": [{"order": "F ALB - TRI", "accepted": true, "result": []}, {"order": "A BUD S F ALB - TRI", "accepted": true, "result": []}, {"order": "A SER S F ALB - TRI", "accepted": true, "result": []}], "ENGLAND": [{"order": "F EDI - NWG", "accepted": true, "result": []}, {"order": "F ENG - NTH", "accepted": true, "result": ["bounce"]}, {"order": "A YOR - LON", "accepted": true, "result": []}], "FRANCE": [{"order": "F BRE - PIC", "accepted": true, "result": []}, {"order": "A MAR - PIE", "accepted": true, "result": []}, {"order": "F MAO - NAO", "accepted": true, "result": []}, {"order": "A PAR - BUR", "accepted": true, "result": []}, {"order": "F SPA/SC - WES", "accepted": true, "result": ["bounce"]}], "GERMANY": [{"order": "A DEN - KIE", "accepted": true, "result": []}, {"order": "F HOL - HEL", "accepted": true, "result": []}, {"order": "A KIE - HOL", "accepted": true, "result": []}, {"order": "A MUN S A PAR - BUR", "accepted": true, "result": []}, {"order": "F NTH S A YOR - LON", "accepted": true, "result": ["cut"]}], "ITALY": [{"order": "F ADR - ALB", "accepted": true, "result": []}, {"order": "A BEL H", "accepted": true, "result": []}, {"order": "F ION S F ALB - GRE", "accepted": true, "result": ["void"]}, {"order": "F NAP H", "accepted": true, "result": []}, {"order": "A TRI S A BUD", "accepted": true, "result": ["cut", "dislodged"]}, {"order": "F TUN - WES", "accepted": true, "result": ["bounce"]}], "RUSSIA": [{"order": "F BLA S A RUM", "accepted": true, "result": []}, {"order": "A GAL S A SIL - BOH", "accepted": true, "result": []}, {"order": "F NWY - SWE", "accepted": true, "result": []}, {"order": "A SIL - BOH", "accepted": true, "result": []}, {"order": "F STP/NC - NWY", "accepted": true, "result": []}, {"order": "F SWE - BAL", "accepted": true, "result": []}], "TURKEY": [{"order": "F AEG - GRE", "accepted": true, "result": []}, {"order": "A BUL S F AEG - GRE", "accepted": true, "result": []}, {"order": "F CON - AEG", "accepted": true, "result": []}, {"order": "A RUM S A GAL", "accepted": true, "result": []}, {"order": "F SMY - EAS", "accepted": true, "result": []}]}
