{"ADR": [], "AEG": [], "ALB": ["F ALB D"], "ANK": ["WAIVE", "F ANK B", "A ANK B"], "APU": [], "ARM": [], "BAL": ["F BAL D"], "BAR": [], "BEL": [], "BER": [], "BLA": ["F BLA D"], "BOH": ["A BOH D"], "BOT": [], "BRE": [], "BUD": [], "BUL/EC": [], "BUL/SC": [], "BUL": [], "BUR": [], "CLY": [], "CON": ["WAIVE", "F CON B", "A CON B"], "DEN": [], "EAS": [], "EDI": [], "ENG": [], "FIN": [], "GAL": ["A GAL D"], "GAS": [], "GRE": [], "HEL": [], "HOL": [], "ION": ["F ION D"], "IRI": [], "KIE": [], "LON": [], "LVN": [], "LVP": ["WAIVE", "A LVP B", "F LVP B"], "LYO": [], "MAO": [], "MAR": [], "MOS": [], "MUN": [], "NAF": [], "NAO": [], "NAP": [], "NWY": ["F NWY D"], "NTH": [], "NWG": [], "PAR": [], "PIC": [], "PIE": [], "POR": [], "PRU": [], "ROM": [], "RUH": ["A RUH D"], "RUM": [], "SER": [], "SEV": [], "SIL": [], "SKA": [], "SMY": ["WAIVE", "A SMY B", "F SMY B"], "SPA/NC": [], "SPA/SC": [], "SPA": [], "STP/NC": [], "STP/SC": [], "STP": [], "SWE": ["F SWE D"], "SYR": [], "TRI": [], "TUN": ["F TUN D"], "TUS": [], "TYR": [], "TYS": ["F TYS D"], "UKR": [], "VEN": ["A VEN D"], "VIE": ["WAIVE", "A VIE B"], "WAL": [], "WAR": [], "WES": [], "YOR": [], "SWI": []}
