{"ADR": [], "AEG": ["F AEG S F GRE", "F AEG S F EAS - ION", "F AEG C A BUL - SMY", "F AEG - GRE", "F AEG S A RUM - BUL", "F AEG C A BUL - APU", "F AEG S A BUL - CON", "F AEG C A BUL - SYR", "F AEG C A BUL - TUN", "F AEG S F BLA - BUL/EC", "F AEG - BUL/SC", "F AEG - CON", "F AEG S F GRE - BUL", "F AEG S F ION - EAS", "F AEG C A BUL - ALB", "F AEG S F ALB - GRE", "F AEG C A BUL - CON", "F AEG S A BUL", "F AEG - EAS", "F AEG S F TUN - ION", "F AEG H", "F AEG S A BUL - GRE", "F AEG - ION", "F AEG S F GRE - ION", "F AEG C A BUL - GRE", "F AEG - SMY", "F AEG S F ION", "F AEG S F GRE - BUL/SC", "F AEG S A SER - GRE", "F AEG S F ALB - ION", "F AEG S F BLA - CON", "F AEG S F BLA - BUL", "F AEG S F EAS", "F AEG S F NAP - ION", "F AEG C A BUL - NAP", "F AEG S A RUM - CON", "F AEG S F EAS - SMY", "F AEG S F ION - GRE", "F AEG S A SER - BUL"], "ALB": ["F ALB - ADR", "F ALB H", "F ALB S F AEG - ION", "F ALB S F GRE - ION", "F ALB S F ION - GRE", "F ALB S A BUL - GRE", "F ALB S F ION", "F ALB S F NAP - ION", "F ALB S F TRI - ADR", "F ALB S F TRI", "F ALB - TRI", "F ALB S A SER - GRE", "F ALB S F AEG - GRE", "F ALB - ION", "F ALB S F ION - ADR", "F ALB - GRE", "F ALB S A SER - TRI", "F ALB S A VEN - TRI", "F ALB S F GRE", "F ALB S F EAS - ION", "F ALB S A BUD - TRI", "F ALB S F TUN - ION"], "ANK": [], "APU": [], "ARM": [], "BAL": ["F BAL C A KIE - SWE", "F BAL C A KIE - BER", "F BAL S A KIE", "F BAL - PRU", "F BAL S A MUN - BER", "F BAL S A BEL - KIE", "F BAL S A KIE - DEN", "F BAL C A KIE - PRU", "F BAL - LVN", "F BAL - DEN", "F BAL S F SWE", "F BAL S F NWY - SWE", "F BAL - KIE", "F BAL S F SWE - BOT", "F BAL S F HEL - KIE", "F BAL - BOT", "F BAL H", "F BAL C A KIE - DEN", "F BAL S F NTH - DEN", "F BAL S F SWE - DEN", "F BAL S F HEL - DEN", "F BAL S A BEL - DEN", "F BAL S A LON - DEN", "F BAL S A HOL - KIE", "F BAL S A LON - KIE", "F BAL S A KIE - BER", "F BAL - BER", "F BAL C A KIE - LVN", "F BAL - SWE", "F BAL S A HOL - DEN", "F BAL S A MUN - KIE"], "BAR": [], "BEL": ["A BEL H", "A BEL S A BUR - PIC", "A BEL S F ENG - PIC", "A BEL S A MUN - BUR", "A BEL - PIC", "A BEL S A KIE - PIC", "A BEL S A LON - HOL", "A BEL - LON VIA", "A BEL - NWY VIA", "A BEL S A LON - PIC", "A BEL - LVP VIA", "A BEL S A BUR", "A BEL S A MUN - RUH", "A BEL S A KIE - HOL", "A BEL S F NTH - HOL", "A BEL S A HOL - PIC", "A BEL - YOR VIA", "A BEL S A BUR - RUH", "A BEL - BRE VIA", "A BEL - WAL VIA", "A BEL S F PIC", "A BEL S F HEL - HOL", "A BEL S A HOL - RUH", "A BEL - EDI VIA", "A BEL - CLY VIA", "A BEL - HOL", "A BEL - PIC VIA", "A BEL S A HOL", "A BEL - HOL VIA", "A BEL S A KIE - RUH", "A BEL - KIE VIA", "A BEL - DEN VIA", "A BEL - BUR", "A BEL - RUH"], "BER": [], "BLA": ["F BLA H", "F BLA C A RUM - ANK", "F BLA S F GRE - BUL", "F BLA - ANK", "F BLA S F AEG - BUL", "F BLA S A SER - RUM", "F BLA - SEV", "F BLA S A RUM", "F BLA - BUL/EC", "F BLA S A BUL - RUM", "F BLA S A SER - BUL", "F BLA C A BUL - ANK", "F BLA S F AEG - CON", "F BLA S A RUM - BUL", "F BLA C A BUL - ARM", "F BLA S A BUL", "F BLA C A RUM - BUL", "F BLA C A RUM - CON", "F BLA S A RUM - SEV", "F BLA - ARM", "F BLA C A RUM - ARM", "F BLA C A BUL - SEV", "F BLA C A BUL - RUM", "F BLA S F GRE - BUL/SC", "F BLA - RUM", "F BLA S A BUD - RUM", "F BLA S F AEG - BUL/SC", "F BLA C A BUL - CON", "F BLA S A BUL - CON", "F BLA C A RUM - SEV", "F BLA - CON", "F BLA S A GAL - RUM"], "BOH": ["A BOH - TYR", "A BOH S A BUD - GAL", "A BOH S A MUN - TYR", "A BOH S A GAL - VIE", "A BOH - MUN", "A BOH S A GAL", "A BOH S A MUN", "A BOH S A PIE - TYR", "A BOH S A GAL - SIL", "A BOH S A KIE - MUN", "A BOH - VIE", "A BOH S A MUN - SIL", "A BOH S A BUR - MUN", "A BOH S A RUM - GAL", "A BOH H", "A BOH S A VEN - TYR", "A BOH S A BUD - VIE", "A BOH - SIL", "A BOH - GAL"], "BOT": [], "BRE": [], "BUD": ["A BUD S A GAL - RUM", "A BUD S F ALB - TRI", "A BUD S A VEN - TRI", "A BUD S A SER - RUM", "A BUD S A GAL", "A BUD S A RUM - GAL", "A BUD - GAL", "A BUD - SER", "A BUD S F TRI", "A BUD H", "A BUD S A BOH - VIE", "A BUD S A SER - TRI", "A BUD S F BLA - RUM", "A BUD S A RUM", "A BUD S A SER", "A BUD - VIE", "A BUD S A BUL - SER", "A BUD - RUM", "A BUD S A BUL - RUM", "A BUD S A GAL - VIE", "A BUD S A RUM - SER", "A BUD - TRI", "A BUD S A BOH - GAL"], "BUL/EC": [], "BUL/SC": [], "BUL": ["A BUL S F ALB - GRE", "A BUL - RUM", "A BUL - SEV VIA", "A BUL S A RUM - CON", "A BUL - TUN VIA", "A BUL - ANK VIA", "A BUL S F AEG - CON", "A BUL - GRE", "A BUL H", "A BUL - RUM VIA", "A BUL S F ION - GRE", "A BUL S A RUM", "A BUL - ARM VIA", "A BUL - SMY VIA", "A BUL - GRE VIA", "A BUL - CON VIA", "A BUL S A SER - RUM", "A BUL S F BLA - CON", "A BUL - ALB VIA", "A BUL - NAP VIA", "A BUL - SER", "A BUL S A GAL - RUM", "A BUL - CON", "A BUL S F AEG - GRE", "A BUL - APU VIA", "A BUL S A SER", "A BUL S A BUD - RUM", "A BUL S F BLA - RUM", "A BUL S A RUM - SER", "A BUL S F GRE", "A BUL S A SER - GRE", "A BUL - SYR VIA", "A BUL S A BUD - SER"], "BUR": ["A BUR - BEL", "A BUR S F PIC - BEL", "A BUR S A KIE - MUN", "A BUR S A KIE - BEL", "A BUR S A LON - BEL", "A BUR S A MUN - RUH", "A BUR S F NTH - BEL", "A BUR S A HOL - PIC", "A BUR S A MUN", "A BUR - PAR", "A BUR S A BEL - RUH", "A BUR S A HOL - BEL", "A BUR S A BEL - PIC", "A BUR S A BOH - MUN", "A BUR S A LON - PIC", "A BUR S A HOL - RUH", "A BUR S A BEL", "A BUR H", "A BUR - MAR", "A BUR - RUH", "A BUR - MUN", "A BUR - GAS", "A BUR S F ENG - PIC", "A BUR S A PIE - MAR", "A BUR - PIC", "A BUR S A KIE - PIC", "A BUR S F PIC", "A BUR S F SPA/SC - MAR", "A BUR S A KIE - RUH", "A BUR S F ENG - BEL"], "CLY": [], "CON": [], "DEN": [], "EAS": ["F EAS H", "F EAS S F ION", "F EAS S F NAP - ION", "F EAS S F TUN - ION", "F EAS S F AEG - ION", "F EAS - SMY", "F EAS S F AEG - SMY", "F EAS S F AEG", "F EAS - SYR", "F EAS S F ION - AEG", "F EAS - AEG", "F EAS S F ALB - ION", "F EAS S F GRE - AEG", "F EAS - ION", "F EAS C A BUL - SYR", "F EAS S A BUL - SMY", "F EAS S F GRE - ION"], "EDI": [], "ENG": ["F ENG - LON", "F ENG C A KIE - WAL", "F ENG S F PIC", "F ENG S A BEL - LON", "F ENG S A KIE - BEL", "F ENG - BEL", "F ENG S A HOL - LON", "F ENG S F NWY - NTH", "F ENG C A HOL - PIC", "F ENG C A LON - BEL", "F ENG S F NTH - LON", "F ENG C A BEL - PIC", "F ENG S F NTH", "F ENG S F NWG - NTH", "F ENG C A LON - BRE", "F ENG C A LON - WAL", "F ENG C A BEL - WAL", "F ENG S A HOL - BEL", "F ENG C A BEL - LON", "F ENG S F PIC - BEL", "F ENG S A BEL", "F ENG S F PIC - BRE", "F ENG - MAO", "F ENG - IRI", "F ENG C A LON - PIC", "F ENG - WAL", "F ENG H", "F ENG - BRE", "F ENG C A HOL - BRE", "F ENG S A BUR - BEL", "F ENG S A LON", "F ENG S A BEL - PIC", "F ENG S F NAO - MAO", "F ENG S F NTH - BEL", "F ENG S F SPA/SC - MAO", "F ENG S A LON - WAL", "F ENG S F NAO - IRI", "F ENG S F HEL - NTH", "F ENG C A KIE - BRE", "F ENG C A HOL - WAL", "F ENG C A BEL - BRE", "F ENG - PIC", "F ENG S A KIE - LON", "F ENG C A KIE - PIC", "F ENG S A BUR - PIC", "F ENG - NTH", "F ENG S A LON - BEL"], "FIN": [], "GAL": ["A GAL - BOH", "A GAL S A SER - RUM", "A GAL S A BOH", "A GAL S A BUD - VIE", "A GAL H", "A GAL S A MUN - BOH", "A GAL - UKR", "A GAL S A BUD", "A GAL S A RUM - UKR", "A GAL - VIE", "A GAL S A RUM - BUD", "A GAL - WAR", "A GAL S A BUD - RUM", "A GAL S A BOH - SIL", "A GAL - SIL", "A GAL - BUD", "A GAL S F BLA - RUM", "A GAL S A MUN - SIL", "A GAL S A BOH - VIE", "A GAL S A SER - BUD", "A GAL S A BUL - RUM", "A GAL S A RUM", "A GAL - RUM"], "GAS": [], "GRE": ["F GRE - ION", "F GRE S F AEG", "F GRE S A BUL", "F GRE - AEG", "F GRE S F ALB", "F GRE S F ION - AEG", "F GRE S A RUM - BUL", "F GRE - BUL/SC", "F GRE S F ION - ALB", "F GRE S F AEG - ION", "F GRE S F EAS - AEG", "F GRE S F AEG - BUL/SC", "F GRE H", "F GRE S F ALB - ION", "F GRE S A SER - BUL", "F GRE S F TUN - ION", "F GRE - ALB", "F GRE S A SER - ALB", "F GRE S F ION", "F GRE S F EAS - ION", "F GRE S F NAP - ION", "F GRE S F BLA - BUL/EC", "F GRE S A BUL - ALB", "F GRE S F TRI - ALB", "F GRE S F AEG - BUL", "F GRE S F BLA - BUL"], "HEL": ["F HEL S A LON - HOL", "F HEL C A KIE - HOL", "F HEL S A LON - DEN", "F HEL C A KIE - BEL", "F HEL C A HOL - KIE", "F HEL C A KIE - LON", "F HEL C A KIE - EDI", "F HEL - HOL", "F HEL - DEN", "F HEL S F NWY - NTH", "F HEL - KIE", "F HEL S A MUN - KIE", "F HEL C A BEL - KIE", "F HEL C A KIE - CLY", "F HEL S F SWE - DEN", "F HEL C A KIE - LVP", "F HEL C A KIE - BRE", "F HEL C A KIE - PIC", "F HEL S A KIE", "F HEL S A KIE - DEN", "F HEL C A LON - KIE", "F HEL S F NWG - NTH", "F HEL S F ENG - NTH", "F HEL C A KIE - WAL", "F HEL - NTH", "F HEL S F BAL - KIE", "F HEL S A KIE - HOL", "F HEL C A HOL - DEN", "F HEL S F NTH - HOL", "F HEL C A KIE - DEN", "F HEL C A KIE - NWY", "F HEL S A BEL - HOL", "F HEL S F BAL - DEN", "F HEL S A BEL - DEN", "F HEL C A KIE - YOR", "F HEL S F NTH", "F HEL S A HOL - KIE", "F HEL S A HOL - DEN", "F HEL S F NTH - DEN", "F HEL H", "F HEL S A HOL"], "HOL": ["A HOL - KIE VIA", "A HOL - BRE VIA", "A HOL - BEL VIA", "A HOL S A BEL - RUH", "A HOL S F HEL - KIE", "A HOL - CLY VIA", "A HOL S F NTH - BEL", "A HOL - LVP VIA", "A HOL S A BEL", "A HOL - NWY VIA", "A HOL S A MUN - RUH", "A HOL - RUH", "A HOL S F PIC - BEL", "A HOL S A KIE", "A HOL S F ENG - BEL", "A HOL S A KIE - RUH", "A HOL - YOR VIA", "A HOL S A MUN - KIE", "A HOL S A LON - KIE", "A HOL S A BUR - BEL", "A HOL S A KIE - BEL", "A HOL - EDI VIA", "A HOL S A BUR - RUH", "A HOL - KIE", "A HOL - BEL", "A HOL - LON VIA", "A HOL - DEN VIA", "A HOL S A BEL - KIE", "A HOL - PIC VIA", "A HOL H", "A HOL S F BAL - KIE", "A HOL - WAL VIA", "A HOL S A LON - BEL"], "ION": ["F ION S F NAP - TYS", "F ION S A SER - GRE", "F ION C A BUL - APU", "F ION S F GRE", "F ION - NAP", "F ION - GRE", "F ION - AEG", "F ION S F NAP", "F ION - APU", "F ION H", "F ION S F NAP - APU", "F ION S F ALB - ADR", "F ION S F AEG - EAS", "F ION - TYS", "F ION S A BUL - GRE", "F ION S A VEN - APU", "F ION S F AEG", "F ION - TUN", "F ION S F EAS", "F ION C A BUL - TUN", "F ION S F AEG - GRE", "F ION S F EAS - AEG", "F ION S A SER - ALB", "F ION S F TUN - TYS", "F ION - ALB", "F ION S F GRE - AEG", "F ION S F GRE - ALB", "F ION - ADR", "F ION C A BUL - ALB", "F ION S F TRI - ADR", "F ION C A BUL - NAP", "F ION S F TUN", "F ION S F TRI - ALB", "F ION - EAS", "F ION S F ALB", "F ION S F ALB - GRE"], "IRI": [], "KIE": ["A KIE S F NTH - HOL", "A KIE - MUN", "A KIE - WAL VIA", "A KIE S A BUR - MUN", "A KIE S A MUN - RUH", "A KIE S F HEL - HOL", "A KIE S A HOL", "A KIE - BER VIA", "A KIE - LVP VIA", "A KIE - HOL", "A KIE - LVN VIA", "A KIE - BRE VIA", "A KIE S F HEL - DEN", "A KIE S A HOL - RUH", "A KIE S A MUN - BER", "A KIE S A MUN", "A KIE S A BOH - MUN", "A KIE - YOR VIA", "A KIE - DEN VIA", "A KIE S A LON - HOL", "A KIE S A BEL - HOL", "A KIE S A BEL - DEN", "A KIE H", "A KIE - BER", "A KIE - LON VIA", "A KIE - HOL VIA", "A KIE S A HOL - DEN", "A KIE - CLY VIA", "A KIE S F BAL - DEN", "A KIE S A BUR - RUH", "A KIE - DEN", "A KIE - EDI VIA", "A KIE - RUH", "A KIE - BEL VIA", "A KIE - PIC VIA", "A KIE - NWY VIA", "A KIE - SWE VIA", "A KIE S F NTH - DEN", "A KIE - PRU VIA", "A KIE S A LON - DEN", "A KIE S F SWE - DEN", "A KIE S F BAL - BER", "A KIE S A BEL - RUH"], "LON": ["A LON - WAL VIA", "A LON - EDI VIA", "A LON - CLY VIA", "A LON - YOR", "A LON - WAL", "A LON - YOR VIA", "A LON - KIE VIA", "A LON - BRE VIA", "A LON S A BEL - WAL", "A LON S A HOL - WAL", "A LON S A BEL - YOR", "A LON - HOL VIA", "A LON S A HOL - YOR", "A LON H", "A LON - NWY VIA", "A LON - PIC VIA", "A LON S A KIE - WAL", "A LON - BEL VIA", "A LON - LVP VIA", "A LON - DEN VIA", "A LON S F ENG - WAL", "A LON S A KIE - YOR", "A LON S F NTH - YOR"], "LVN": [], "LVP": [], "LYO": [], "MAO": [], "MAR": [], "MOS": [], "MUN": ["A MUN S A BOH - TYR", "A MUN S F BAL - KIE", "A MUN S A BEL - RUH", "A MUN S A VEN - TYR", "A MUN S A KIE", "A MUN - BUR", "A MUN S A HOL - RUH", "A MUN S A BOH", "A MUN S A KIE - RUH", "A MUN S A BEL - KIE", "A MUN S A BEL - BUR", "A MUN S F BAL - BER", "A MUN - BOH", "A MUN S A GAL - BOH", "A MUN H", "A MUN S F HEL - KIE", "A MUN - KIE", "A MUN S A HOL - KIE", "A MUN - BER", "A MUN S A BOH - SIL", "A MUN S A GAL - SIL", "A MUN - RUH", "A MUN S A PIE - TYR", "A MUN - TYR", "A MUN S A KIE - BER", "A MUN S A BUR - RUH", "A MUN - SIL", "A MUN S A BUR", "A MUN S A LON - KIE"], "NAF": [], "NAO": ["F NAO S A KIE - CLY", "F NAO S A BEL - CLY", "F NAO - NWG", "F NAO S F NWG", "F NAO S A LON - CLY", "F NAO C A LON - LVP", "F NAO C A HOL - LVP", "F NAO S F ENG - MAO", "F NAO C A KIE - LVP", "F NAO H", "F NAO S A HOL - CLY", "F NAO S F NTH - NWG", "F NAO - MAO", "F NAO S F SPA/SC - MAO", "F NAO S F NWY - NWG", "F NAO S F NWG - CLY", "F NAO - IRI", "F NAO - CLY", "F NAO C A BEL - LVP", "F NAO S F ENG - IRI", "F NAO - LVP"], "NAP": ["F NAP S A VEN - APU", "F NAP S F TUN - TYS", "F NAP S F GRE - ION", "F NAP S F EAS - ION", "F NAP - APU", "F NAP S F ION - APU", "F NAP H", "F NAP S A VEN - ROM", "F NAP - TYS", "F NAP - ROM", "F NAP S F ALB - ION", "F NAP S F TUN - ION", "F NAP S F AEG - ION", "F NAP S F ION", "F NAP S A BUL - APU", "F NAP - ION", "F NAP S F ION - TYS"], "NWY": ["F NWY S F NTH - NWG", "F NWY - STP/NC", "F NWY S F NWG", "F NWY S A KIE - SWE", "F NWY S F ENG - NTH", "F NWY S F HEL - NTH", "F NWY - BAR", "F NWY S F SWE - SKA", "F NWY - NWG", "F NWY S F NWG - NTH", "F NWY - SWE", "F NWY S F NAO - NWG", "F NWY S F BAL - SWE", "F NWY S F NTH - SKA", "F NWY H", "F NWY S F NTH", "F NWY - SKA", "F NWY S F NWG - BAR", "F NWY S F SWE", "F NWY - NTH"], "NTH": ["F NTH C A LON - CLY", "F NTH C A KIE - BEL", "F NTH - EDI", "F NTH H", "F NTH - LON", "F NTH C A BEL - HOL", "F NTH S F NAO - NWG", "F NTH C A HOL - LVP", "F NTH C A HOL - BEL", "F NTH - HOL", "F NTH C A BEL - LON", "F NTH C A BEL - LVP", "F NTH C A KIE - PIC", "F NTH C A BEL - EDI", "F NTH S F HEL - DEN", "F NTH S F BAL - DEN", "F NTH S F PIC - ENG", "F NTH S A BEL - LON", "F NTH C A KIE - LON", "F NTH C A LON - BEL", "F NTH C A LON - YOR", "F NTH C A KIE - CLY", "F NTH C A BEL - NWY", "F NTH S A HOL - BEL", "F NTH S F HEL - HOL", "F NTH S F ENG", "F NTH S F SWE - SKA", "F NTH S A BUR - BEL", "F NTH C A HOL - LON", "F NTH S A BEL - HOL", "F NTH S A KIE - HOL", "F NTH C A LON - KIE", "F NTH - YOR", "F NTH C A HOL - EDI", "F NTH C A BEL - DEN", "F NTH - NWY", "F NTH - BEL", "F NTH C A KIE - EDI", "F NTH C A BEL - CLY", "F NTH S A HOL - DEN", "F NTH C A KIE - NWY", "F NTH S A LON - BEL", "F NTH S F NWG - NWY", "F NTH - SKA", "F NTH S F ENG - BEL", "F NTH C A HOL - NWY", "F NTH C A KIE - YOR", "F NTH C A BEL - KIE", "F NTH - HEL", "F NTH S F NWG", "F NTH C A KIE - WAL", "F NTH S F HEL", "F NTH C A HOL - WAL", "F NTH S F SWE - DEN", "F NTH C A LON - LVP", "F NTH C A BEL - YOR", "F NTH C A HOL - CLY", "F NTH S A KIE - DEN", "F NTH S A BEL", "F NTH C A KIE - BRE", "F NTH C A LON - EDI", "F NTH S F SWE - NWY", "F NTH S F ENG - LON", "F NTH - ENG", "F NTH C A LON - DEN", "F NTH S A HOL", "F NTH S F NWY - SKA", "F NTH C A HOL - PIC", "F NTH - DEN", "F NTH S F PIC - BEL", "F NTH C A HOL - YOR", "F NTH S F NWY", "F NTH C A HOL - DEN", "F NTH C A LON - NWY", "F NTH S A LON", "F NTH - NWG", "F NTH S A LON - YOR", "F NTH C A LON - HOL", "F NTH C A KIE - LVP", "F NTH C A HOL - BRE", "F NTH S F NWG - EDI", "F NTH S F NWY - NWG"], "NWG": ["F NWG S F NTH - NWY", "F NWG C A HOL - LVP", "F NWG S F NAO - CLY", "F NWG S A HOL - EDI", "F NWG - NTH", "F NWG C A KIE - CLY", "F NWG S A HOL - NWY", "F NWG C A LON - LVP", "F NWG C A KIE - LVP", "F NWG S F ENG - NTH", "F NWG S F HEL - NTH", "F NWG C A LON - CLY", "F NWG H", "F NWG S A BEL - NWY", "F NWG S F NTH - EDI", "F NWG S F NWY - BAR", "F NWG - NWY", "F NWG S A LON - NWY", "F NWG S A BEL - EDI", "F NWG S A KIE - NWY", "F NWG - NAO", "F NWG S A LON - EDI", "F NWG C A HOL - CLY", "F NWG C A BEL - LVP", "F NWG S F SWE - NWY", "F NWG - EDI", "F NWG S A KIE - EDI", "F NWG - CLY", "F NWG S F NTH", "F NWG - BAR", "F NWG C A BEL - CLY", "F NWG S F NWY", "F NWG S F NAO", "F NWG S F NWY - NTH"], "PAR": [], "PIC": ["F PIC - BRE", "F PIC - BEL", "F PIC S F NTH - ENG", "F PIC S A BUR - BEL", "F PIC S A BEL", "F PIC S A KIE - BRE", "F PIC S A LON - BRE", "F PIC S A LON - BEL", "F PIC S F NTH - BEL", "F PIC - ENG", "F PIC S F ENG - BRE", "F PIC S A KIE - BEL", "F PIC S F ENG - BEL", "F PIC S A HOL - BEL", "F PIC H", "F PIC S F ENG", "F PIC S A BEL - BRE", "F PIC S A HOL - BRE"], "PIE": ["A PIE S A VEN - TYR", "A PIE - MAR", "A PIE - VEN", "A PIE S A BUR - MAR", "A PIE S A BOH - TYR", "A PIE S F SPA/SC - MAR", "A PIE S F TRI - VEN", "A PIE H", "A PIE - TUS", "A PIE - TYR", "A PIE S A MUN - TYR", "A PIE S A VEN - TUS", "A PIE S A VEN"], "POR": [], "PRU": [], "ROM": [], "RUH": [], "RUM": ["A RUM S A SER", "A RUM - CON VIA", "A RUM - ANK VIA", "A RUM - BUD", "A RUM H", "A RUM - SER", "A RUM S A SER - BUL", "A RUM - BUL", "A RUM - GAL", "A RUM S A BUL", "A RUM S A SER - BUD", "A RUM S A BOH - GAL", "A RUM - BUL VIA", "A RUM - SEV VIA", "A RUM S F BLA - BUL", "A RUM S A GAL", "A RUM S A GAL - UKR", "A RUM S A GAL - BUD", "A RUM S A BUD", "A RUM - ARM VIA", "A RUM S F BLA - BUL/EC", "A RUM S F BLA - SEV", "A RUM - SEV", "A RUM S F AEG - BUL/SC", "A RUM S A BUD - GAL", "A RUM S F GRE - BUL/SC", "A RUM S A BUL - SER", "A RUM - UKR", "A RUM S A BUD - SER", "A RUM S F AEG - BUL", "A RUM S A BUL - SEV", "A RUM S F GRE - BUL"], "SER": ["A SER - RUM", "A SER S F ALB", "A SER S F GRE - ALB", "A SER S A BUL", "A SER S F AEG - GRE", "A SER S F GRE - BUL/SC", "A SER H", "A SER S A BUL - ALB", "A SER S A BUD - RUM", "A SER S A RUM", "A SER S F ION - ALB", "A SER S F AEG - BUL", "A SER S A GAL - RUM", "A SER S F BLA - RUM", "A SER S A BUL - RUM", "A SER S F GRE", "A SER - BUD", "A SER S A BUD - TRI", "A SER S F AEG - BUL/SC", "A SER - BUL", "A SER S F ALB - GRE", "A SER S F GRE - BUL", "A SER S A GAL - BUD", "A SER - ALB", "A SER - TRI", "A SER S F BLA - BUL/EC", "A SER S F ION - GRE", "A SER S A RUM - BUL", "A SER S F BLA - BUL", "A SER S F TRI - ALB", "A SER S A RUM - BUD", "A SER S A VEN - TRI", "A SER S A BUL - GRE", "A SER S F ALB - TRI", "A SER S F TRI", "A SER S A BUD", "A SER - GRE"], "SEV": [], "SIL": [], "SKA": [], "SMY": [], "SPA/NC": [], "SPA/SC": ["F SPA/SC - WES", "F SPA/SC - LYO", "F SPA/SC - MAO", "F SPA/SC S F TUN - WES", "F SPA/SC S F ENG - MAO", "F SPA/SC S A PIE - MAR", "F SPA/SC H", "F SPA/SC S F NAO - MAO", "F SPA/SC - POR", "F SPA/SC - MAR", "F SPA/SC S A BUR - MAR"], "SPA": ["F SPA/SC - WES", "F SPA/SC - LYO", "F SPA/SC - MAO", "F SPA/SC S F TUN - WES", "F SPA/SC S F ENG - MAO", "F SPA/SC S A PIE - MAR", "F SPA/SC H", "F SPA/SC S F NAO - MAO", "F SPA/SC - POR", "F SPA/SC - MAR", "F SPA/SC S A BUR - MAR"], "STP/NC": [], "STP/SC": [], "STP": [], "SWE": ["F SWE S A BEL - DEN", "F SWE S A LON - NWY", "F SWE S A HOL - NWY", "F SWE S F HEL - DEN", "F SWE S A KIE - DEN", "F SWE - DEN", "F SWE S F NTH - NWY", "F SWE S F NTH - DEN", "F SWE S F NWY", "F SWE S F BAL - BOT", "F SWE - BAL", "F SWE - BOT", "F SWE S F BAL", "F SWE S A BEL - NWY", "F SWE - FIN", "F SWE - SKA", "F SWE S A KIE - NWY", "F SWE - NWY", "F SWE H", "F SWE S F NWY - SKA", "F SWE S F NTH - SKA", "F SWE S A LON - DEN", "F SWE S A HOL - DEN", "F SWE S F NWG - NWY", "F SWE S F BAL - DEN"], "SYR": [], "TRI": ["F TRI S A BUL - ALB", "F TRI H", "F TRI - VEN", "F TRI S F ALB", "F TRI S F GRE - ALB", "F TRI S A SER - ALB", "F TRI S F ION - ADR", "F TRI S A VEN", "F TRI - ALB", "F TRI - ADR", "F TRI S F ALB - ADR", "F TRI S A PIE - VEN", "F TRI S F ION - ALB"], "TUN": ["F TUN S F ALB - ION", "F TUN S F GRE - ION", "F TUN S F ION", "F TUN S F SPA/SC - WES", "F TUN S F NAP - ION", "F TUN S F EAS - ION", "F TUN - ION", "F TUN S F NAP - TYS", "F TUN - TYS", "F TUN - NAF", "F TUN S F ION - TYS", "F TUN S F AEG - ION", "F TUN H", "F TUN - WES"], "TUS": [], "TYR": [], "TYS": [], "UKR": [], "VEN": ["A VEN H", "A VEN - ROM", "A VEN S A PIE - TYR", "A VEN S A SER - TRI", "A VEN S F NAP - ROM", "A VEN S F ALB - TRI", "A VEN S F TRI", "A VEN S A PIE - TUS", "A VEN S F ION - APU", "A VEN S A MUN - TYR", "A VEN - TUS", "A VEN S F NAP - APU", "A VEN S A BOH - TYR", "A VEN - PIE", "A VEN S A BUL - APU", "A VEN - APU", "A VEN - TRI", "A VEN S A PIE", "A VEN S A BUD - TRI", "A VEN - TYR"], "VIE": [], "WAL": [], "WAR": [], "WES": [], "YOR": [], "SWI": []}
